texasbbq.py
texasbbq-0.1.0.dist-info/LICENSE
texasbbq-0.1.0.dist-info/METADATA
texasbbq-0.1.0.dist-info/WHEEL
texasbbq-0.1.0.dist-info/top_level.txt
texasbbq-0.1.0.dist-info/RECORD
